Metadata-Version: 2.1
Name: MAHA
Version: 1.3
Summary: Performing ETL using Machine Learning
Home-page: https://github.com/user/FlintyTub49
Author: Mithesh R, Arth Akhouri, Heetansh Jhaveri, Ayaan Khan
Author-email: arthakhouri@gmail.com
License: MIT
Download-URL: https://github.com/FlintyTub49/MAHA/archive/1.3.tar.gz
Keywords: ETL,Machine Learning,Regression,Pandas,Numpy
Platform: UNKNOWN
Classifier: Development Status :: 3 - Alpha
Classifier: Intended Audience :: Developers
Classifier: Topic :: Software Development :: Build Tools
Classifier: License :: OSI Approved :: MIT License
Classifier: Programming Language :: Python :: 3
Classifier: Programming Language :: Python :: 3.4
Classifier: Programming Language :: Python :: 3.5
Classifier: Programming Language :: Python :: 3.6
